{
  "agency_id": "pasadena-transit",
  "observations": [
    {
      "coverage_pct": null,
      "kinds_reachable": 2,
      "kinds_total": 2,
      "ts": 1782184337,
      "worst_lag_seconds": 3
    },
    {
      "coverage_pct": null,
      "kinds_reachable": 2,
      "kinds_total": 2,
      "ts": 1782192295,
      "worst_lag_seconds": 5
    },
    {
      "coverage_pct": null,
      "kinds_reachable": 2,
      "kinds_total": 2,
      "ts": 1782202578,
      "worst_lag_seconds": 4
    },
    {
      "coverage_pct": null,
      "kinds_reachable": 2,
      "kinds_total": 2,
      "ts": 1782213118,
      "worst_lag_seconds": 4
    },
    {
      "coverage_pct": null,
      "kinds_reachable": 2,
      "kinds_total": 2,
      "ts": 1782223307,
      "worst_lag_seconds": 3
    },
    {
      "coverage_pct": null,
      "kinds_reachable": 2,
      "kinds_total": 2,
      "ts": 1782233629,
      "worst_lag_seconds": 4
    },
    {
      "coverage_pct": null,
      "kinds_reachable": 2,
      "kinds_total": 2,
      "ts": 1782243743,
      "worst_lag_seconds": 4
    },
    {
      "coverage_pct": null,
      "kinds_reachable": 2,
      "kinds_total": 2,
      "ts": 1782254026,
      "worst_lag_seconds": 1
    },
    {
      "coverage_pct": null,
      "kinds_reachable": 2,
      "kinds_total": 2,
      "ts": 1782266287,
      "worst_lag_seconds": 2
    },
    {
      "coverage_pct": null,
      "kinds_reachable": 2,
      "kinds_total": 2,
      "ts": 1782278814,
      "worst_lag_seconds": 4
    },
    {
      "coverage_pct": null,
      "kinds_reachable": 2,
      "kinds_total": 2,
      "ts": 1782288762,
      "worst_lag_seconds": 2
    },
    {
      "coverage_pct": null,
      "kinds_reachable": 2,
      "kinds_total": 2,
      "ts": 1782299304,
      "worst_lag_seconds": 4
    },
    {
      "coverage_pct": null,
      "kinds_reachable": 2,
      "kinds_total": 2,
      "ts": 1782308996,
      "worst_lag_seconds": 1
    },
    {
      "coverage_pct": null,
      "kinds_reachable": 2,
      "kinds_total": 2,
      "ts": 1782319559,
      "worst_lag_seconds": 5
    },
    {
      "coverage_pct": null,
      "kinds_reachable": 2,
      "kinds_total": 2,
      "ts": 1782330127,
      "worst_lag_seconds": 3
    },
    {
      "coverage_pct": null,
      "kinds_reachable": 2,
      "kinds_total": 2,
      "ts": 1782340243,
      "worst_lag_seconds": 4
    },
    {
      "coverage_pct": null,
      "kinds_reachable": 2,
      "kinds_total": 2,
      "ts": 1782352939,
      "worst_lag_seconds": 4
    },
    {
      "coverage_pct": null,
      "kinds_reachable": 2,
      "kinds_total": 2,
      "ts": 1782365170,
      "worst_lag_seconds": 5
    },
    {
      "coverage_pct": null,
      "kinds_reachable": 2,
      "kinds_total": 2,
      "ts": 1782375237,
      "worst_lag_seconds": 2
    },
    {
      "coverage_pct": null,
      "kinds_reachable": 2,
      "kinds_total": 2,
      "ts": 1782385411,
      "worst_lag_seconds": 2
    },
    {
      "coverage_pct": null,
      "kinds_reachable": 2,
      "kinds_total": 2,
      "ts": 1782395345,
      "worst_lag_seconds": 5
    },
    {
      "coverage_pct": null,
      "kinds_reachable": 2,
      "kinds_total": 2,
      "ts": 1782406251,
      "worst_lag_seconds": 1
    },
    {
      "coverage_pct": null,
      "kinds_reachable": 2,
      "kinds_total": 2,
      "ts": 1782416543,
      "worst_lag_seconds": 4
    },
    {
      "coverage_pct": null,
      "kinds_reachable": 2,
      "kinds_total": 2,
      "ts": 1782427084,
      "worst_lag_seconds": 5
    },
    {
      "coverage_pct": null,
      "kinds_reachable": 2,
      "kinds_total": 2,
      "ts": 1782439507,
      "worst_lag_seconds": 3
    },
    {
      "coverage_pct": null,
      "kinds_reachable": 2,
      "kinds_total": 2,
      "ts": 1782451748,
      "worst_lag_seconds": 3
    },
    {
      "coverage_pct": null,
      "kinds_reachable": 2,
      "kinds_total": 2,
      "ts": 1782461968,
      "worst_lag_seconds": 4
    },
    {
      "coverage_pct": null,
      "kinds_reachable": 2,
      "kinds_total": 2,
      "ts": 1782472100,
      "worst_lag_seconds": 1
    },
    {
      "coverage_pct": null,
      "kinds_reachable": 2,
      "kinds_total": 2,
      "ts": 1782481473,
      "worst_lag_seconds": 3
    },
    {
      "coverage_pct": null,
      "kinds_reachable": 2,
      "kinds_total": 2,
      "ts": 1782492345,
      "worst_lag_seconds": 1
    },
    {
      "coverage_pct": null,
      "kinds_reachable": 2,
      "kinds_total": 2,
      "ts": 1782502892,
      "worst_lag_seconds": 2
    },
    {
      "coverage_pct": null,
      "kinds_reachable": 2,
      "kinds_total": 2,
      "ts": 1782512877,
      "worst_lag_seconds": 3
    },
    {
      "coverage_pct": null,
      "kinds_reachable": 2,
      "kinds_total": 2,
      "ts": 1782525692,
      "worst_lag_seconds": 3
    },
    {
      "coverage_pct": null,
      "kinds_reachable": 2,
      "kinds_total": 2,
      "ts": 1782537788,
      "worst_lag_seconds": 4
    },
    {
      "coverage_pct": null,
      "kinds_reachable": 2,
      "kinds_total": 2,
      "ts": 1782547668,
      "worst_lag_seconds": 3
    },
    {
      "coverage_pct": null,
      "kinds_reachable": 2,
      "kinds_total": 2,
      "ts": 1782556895,
      "worst_lag_seconds": 1
    },
    {
      "coverage_pct": null,
      "kinds_reachable": 2,
      "kinds_total": 2,
      "ts": 1782567025,
      "worst_lag_seconds": 4
    },
    {
      "coverage_pct": null,
      "kinds_reachable": 2,
      "kinds_total": 2,
      "ts": 1782577888,
      "worst_lag_seconds": 4
    },
    {
      "coverage_pct": null,
      "kinds_reachable": 2,
      "kinds_total": 2,
      "ts": 1782588590,
      "worst_lag_seconds": 1
    },
    {
      "coverage_pct": null,
      "kinds_reachable": 2,
      "kinds_total": 2,
      "ts": 1782599033,
      "worst_lag_seconds": 4
    },
    {
      "coverage_pct": null,
      "kinds_reachable": 2,
      "kinds_total": 2,
      "ts": 1782612462,
      "worst_lag_seconds": 3
    },
    {
      "coverage_pct": null,
      "kinds_reachable": 2,
      "kinds_total": 2,
      "ts": 1782624797,
      "worst_lag_seconds": 3
    },
    {
      "coverage_pct": null,
      "kinds_reachable": 2,
      "kinds_total": 2,
      "ts": 1782634988,
      "worst_lag_seconds": 4
    },
    {
      "coverage_pct": null,
      "kinds_reachable": 2,
      "kinds_total": 2,
      "ts": 1782644136,
      "worst_lag_seconds": 2
    },
    {
      "coverage_pct": null,
      "kinds_reachable": 2,
      "kinds_total": 2,
      "ts": 1782653405,
      "worst_lag_seconds": 5
    },
    {
      "coverage_pct": null,
      "kinds_reachable": 2,
      "kinds_total": 2,
      "ts": 1782664143,
      "worst_lag_seconds": 3
    },
    {
      "coverage_pct": null,
      "kinds_reachable": 2,
      "kinds_total": 2,
      "ts": 1782674757,
      "worst_lag_seconds": 3
    },
    {
      "coverage_pct": null,
      "kinds_reachable": 2,
      "kinds_total": 2,
      "ts": 1782685444,
      "worst_lag_seconds": 5
    },
    {
      "coverage_pct": null,
      "kinds_reachable": 2,
      "kinds_total": 2,
      "ts": 1782698983,
      "worst_lag_seconds": 3
    },
    {
      "coverage_pct": null,
      "kinds_reachable": 2,
      "kinds_total": 2,
      "ts": 1782711507,
      "worst_lag_seconds": 3
    },
    {
      "coverage_pct": null,
      "kinds_reachable": 2,
      "kinds_total": 2,
      "ts": 1782723160,
      "worst_lag_seconds": 5
    },
    {
      "coverage_pct": null,
      "kinds_reachable": 2,
      "kinds_total": 2,
      "ts": 1782733232,
      "worst_lag_seconds": 3
    },
    {
      "coverage_pct": null,
      "kinds_reachable": 2,
      "kinds_total": 2,
      "ts": 1782743607,
      "worst_lag_seconds": 3
    },
    {
      "coverage_pct": null,
      "kinds_reachable": 2,
      "kinds_total": 2,
      "ts": 1782753262,
      "worst_lag_seconds": 3
    },
    {
      "coverage_pct": null,
      "kinds_reachable": 2,
      "kinds_total": 2,
      "ts": 1782762122,
      "worst_lag_seconds": 2
    },
    {
      "coverage_pct": null,
      "kinds_reachable": 2,
      "kinds_total": 2,
      "ts": 1782772232,
      "worst_lag_seconds": 3
    },
    {
      "coverage_pct": null,
      "kinds_reachable": 2,
      "kinds_total": 2,
      "ts": 1782784982,
      "worst_lag_seconds": 2
    },
    {
      "coverage_pct": null,
      "kinds_reachable": 2,
      "kinds_total": 2,
      "ts": 1782799327,
      "worst_lag_seconds": 3
    },
    {
      "coverage_pct": null,
      "kinds_reachable": 2,
      "kinds_total": 2,
      "ts": 1782807922,
      "worst_lag_seconds": 3
    },
    {
      "coverage_pct": null,
      "kinds_reachable": 2,
      "kinds_total": 2,
      "ts": 1782818156,
      "worst_lag_seconds": 1
    },
    {
      "coverage_pct": null,
      "kinds_reachable": 2,
      "kinds_total": 2,
      "ts": 1782827205,
      "worst_lag_seconds": 5
    },
    {
      "coverage_pct": null,
      "kinds_reachable": 2,
      "kinds_total": 2,
      "ts": 1782838606,
      "worst_lag_seconds": 2
    },
    {
      "coverage_pct": null,
      "kinds_reachable": 2,
      "kinds_total": 2,
      "ts": 1782848639,
      "worst_lag_seconds": 5
    },
    {
      "coverage_pct": null,
      "kinds_reachable": 2,
      "kinds_total": 2,
      "ts": 1782859118,
      "worst_lag_seconds": 4
    },
    {
      "coverage_pct": null,
      "kinds_reachable": 2,
      "kinds_total": 2,
      "ts": 1782871974,
      "worst_lag_seconds": 5
    },
    {
      "coverage_pct": null,
      "kinds_reachable": 2,
      "kinds_total": 2,
      "ts": 1782945411,
      "worst_lag_seconds": 2
    },
    {
      "coverage_pct": null,
      "kinds_reachable": 2,
      "kinds_total": 2,
      "ts": 1782958106,
      "worst_lag_seconds": 2
    },
    {
      "coverage_pct": null,
      "kinds_reachable": 2,
      "kinds_total": 2,
      "ts": 1782977899,
      "worst_lag_seconds": 5
    },
    {
      "coverage_pct": null,
      "kinds_reachable": 2,
      "kinds_total": 2,
      "ts": 1782995498,
      "worst_lag_seconds": 4
    },
    {
      "coverage_pct": null,
      "kinds_reachable": 2,
      "kinds_total": 2,
      "ts": 1783005413,
      "worst_lag_seconds": 4
    },
    {
      "coverage_pct": null,
      "kinds_reachable": 2,
      "kinds_total": 2,
      "ts": 1783014576,
      "worst_lag_seconds": 2
    },
    {
      "coverage_pct": null,
      "kinds_reachable": 2,
      "kinds_total": 2,
      "ts": 1783024804,
      "worst_lag_seconds": 4
    },
    {
      "coverage_pct": null,
      "kinds_reachable": 2,
      "kinds_total": 2,
      "ts": 1783033639,
      "worst_lag_seconds": 5
    },
    {
      "coverage_pct": null,
      "kinds_reachable": 2,
      "kinds_total": 2,
      "ts": 1783054587,
      "worst_lag_seconds": 3
    },
    {
      "coverage_pct": null,
      "kinds_reachable": 2,
      "kinds_total": 2,
      "ts": 1783074213,
      "worst_lag_seconds": 4
    },
    {
      "coverage_pct": null,
      "kinds_reachable": 2,
      "kinds_total": 2,
      "ts": 1783092112,
      "worst_lag_seconds": 3
    },
    {
      "coverage_pct": null,
      "kinds_reachable": 2,
      "kinds_total": 2,
      "ts": 1783158695,
      "worst_lag_seconds": 1
    },
    {
      "coverage_pct": null,
      "kinds_reachable": 2,
      "kinds_total": 2,
      "ts": 1783165801,
      "worst_lag_seconds": 2
    },
    {
      "coverage_pct": null,
      "kinds_reachable": 2,
      "kinds_total": 2,
      "ts": 1783176574,
      "worst_lag_seconds": 5
    }
  ],
  "summary": {
    "first_ts": 1782184337,
    "last_ts": 1783176574,
    "median_coverage_pct": null,
    "median_lag_seconds": 3,
    "observations": 79,
    "uptime_pct": 100.0
  }
}
