{
  "agency_id": "south-shore-line",
  "observations": [
    {
      "coverage_pct": null,
      "kinds_reachable": 3,
      "kinds_total": 3,
      "ts": 1782184747,
      "worst_lag_seconds": 2
    },
    {
      "coverage_pct": null,
      "kinds_reachable": 3,
      "kinds_total": 3,
      "ts": 1782192851,
      "worst_lag_seconds": 4
    },
    {
      "coverage_pct": null,
      "kinds_reachable": 3,
      "kinds_total": 3,
      "ts": 1782202993,
      "worst_lag_seconds": 5
    },
    {
      "coverage_pct": null,
      "kinds_reachable": 3,
      "kinds_total": 3,
      "ts": 1782213498,
      "worst_lag_seconds": 4
    },
    {
      "coverage_pct": null,
      "kinds_reachable": 3,
      "kinds_total": 3,
      "ts": 1782223700,
      "worst_lag_seconds": 1
    },
    {
      "coverage_pct": null,
      "kinds_reachable": 3,
      "kinds_total": 3,
      "ts": 1782234030,
      "worst_lag_seconds": 3
    },
    {
      "coverage_pct": null,
      "kinds_reachable": 3,
      "kinds_total": 3,
      "ts": 1782244145,
      "worst_lag_seconds": 5
    },
    {
      "coverage_pct": null,
      "kinds_reachable": 3,
      "kinds_total": 3,
      "ts": 1782254406,
      "worst_lag_seconds": 4
    },
    {
      "coverage_pct": null,
      "kinds_reachable": 3,
      "kinds_total": 3,
      "ts": 1782266677,
      "worst_lag_seconds": 5
    },
    {
      "coverage_pct": null,
      "kinds_reachable": 3,
      "kinds_total": 3,
      "ts": 1782279213,
      "worst_lag_seconds": 3
    },
    {
      "coverage_pct": null,
      "kinds_reachable": 3,
      "kinds_total": 3,
      "ts": 1782289140,
      "worst_lag_seconds": 4
    },
    {
      "coverage_pct": null,
      "kinds_reachable": 3,
      "kinds_total": 3,
      "ts": 1782299863,
      "worst_lag_seconds": 3
    },
    {
      "coverage_pct": null,
      "kinds_reachable": 3,
      "kinds_total": 3,
      "ts": 1782309409,
      "worst_lag_seconds": 4
    },
    {
      "coverage_pct": null,
      "kinds_reachable": 3,
      "kinds_total": 3,
      "ts": 1782319969,
      "worst_lag_seconds": 3
    },
    {
      "coverage_pct": null,
      "kinds_reachable": 3,
      "kinds_total": 3,
      "ts": 1782330539,
      "worst_lag_seconds": 3
    },
    {
      "coverage_pct": null,
      "kinds_reachable": 3,
      "kinds_total": 3,
      "ts": 1782340637,
      "worst_lag_seconds": 5
    },
    {
      "coverage_pct": null,
      "kinds_reachable": 3,
      "kinds_total": 3,
      "ts": 1782353352,
      "worst_lag_seconds": 5
    },
    {
      "coverage_pct": null,
      "kinds_reachable": 3,
      "kinds_total": 3,
      "ts": 1782365581,
      "worst_lag_seconds": 4
    },
    {
      "coverage_pct": null,
      "kinds_reachable": 3,
      "kinds_total": 3,
      "ts": 1782375827,
      "worst_lag_seconds": 2
    },
    {
      "coverage_pct": null,
      "kinds_reachable": 3,
      "kinds_total": 3,
      "ts": 1782385808,
      "worst_lag_seconds": 1
    },
    {
      "coverage_pct": null,
      "kinds_reachable": 3,
      "kinds_total": 3,
      "ts": 1782395906,
      "worst_lag_seconds": 0
    },
    {
      "coverage_pct": null,
      "kinds_reachable": 3,
      "kinds_total": 3,
      "ts": 1782406665,
      "worst_lag_seconds": 3
    },
    {
      "coverage_pct": null,
      "kinds_reachable": 3,
      "kinds_total": 3,
      "ts": 1782416956,
      "worst_lag_seconds": 3
    },
    {
      "coverage_pct": null,
      "kinds_reachable": 3,
      "kinds_total": 3,
      "ts": 1782427493,
      "worst_lag_seconds": 3
    },
    {
      "coverage_pct": null,
      "kinds_reachable": 3,
      "kinds_total": 3,
      "ts": 1782439891,
      "worst_lag_seconds": 4
    },
    {
      "coverage_pct": null,
      "kinds_reachable": 3,
      "kinds_total": 3,
      "ts": 1782452134,
      "worst_lag_seconds": 5
    },
    {
      "coverage_pct": null,
      "kinds_reachable": 3,
      "kinds_total": 3,
      "ts": 1782462375,
      "worst_lag_seconds": 4
    },
    {
      "coverage_pct": null,
      "kinds_reachable": 3,
      "kinds_total": 3,
      "ts": 1782472513,
      "worst_lag_seconds": 2
    },
    {
      "coverage_pct": null,
      "kinds_reachable": 3,
      "kinds_total": 3,
      "ts": 1782481888,
      "worst_lag_seconds": 5
    },
    {
      "coverage_pct": null,
      "kinds_reachable": 3,
      "kinds_total": 3,
      "ts": 1782492766,
      "worst_lag_seconds": 4
    },
    {
      "coverage_pct": null,
      "kinds_reachable": 3,
      "kinds_total": 3,
      "ts": 1782503305,
      "worst_lag_seconds": 4
    },
    {
      "coverage_pct": null,
      "kinds_reachable": 3,
      "kinds_total": 3,
      "ts": 1782513288,
      "worst_lag_seconds": 0
    },
    {
      "coverage_pct": null,
      "kinds_reachable": 3,
      "kinds_total": 3,
      "ts": 1782526249,
      "worst_lag_seconds": 4
    },
    {
      "coverage_pct": null,
      "kinds_reachable": 3,
      "kinds_total": 3,
      "ts": 1782538353,
      "worst_lag_seconds": 3
    },
    {
      "coverage_pct": null,
      "kinds_reachable": 3,
      "kinds_total": 3,
      "ts": 1782548080,
      "worst_lag_seconds": 1
    },
    {
      "coverage_pct": null,
      "kinds_reachable": 3,
      "kinds_total": 3,
      "ts": 1782557452,
      "worst_lag_seconds": 0
    },
    {
      "coverage_pct": null,
      "kinds_reachable": 3,
      "kinds_total": 3,
      "ts": 1782567586,
      "worst_lag_seconds": 4
    },
    {
      "coverage_pct": null,
      "kinds_reachable": 3,
      "kinds_total": 3,
      "ts": 1782578447,
      "worst_lag_seconds": 4
    },
    {
      "coverage_pct": null,
      "kinds_reachable": 3,
      "kinds_total": 3,
      "ts": 1782588997,
      "worst_lag_seconds": 5
    },
    {
      "coverage_pct": null,
      "kinds_reachable": 3,
      "kinds_total": 3,
      "ts": 1782599440,
      "worst_lag_seconds": 1
    },
    {
      "coverage_pct": null,
      "kinds_reachable": 3,
      "kinds_total": 3,
      "ts": 1782612884,
      "worst_lag_seconds": 3
    },
    {
      "coverage_pct": null,
      "kinds_reachable": 3,
      "kinds_total": 3,
      "ts": 1782625195,
      "worst_lag_seconds": 3
    },
    {
      "coverage_pct": null,
      "kinds_reachable": 3,
      "kinds_total": 3,
      "ts": 1782635394,
      "worst_lag_seconds": 4
    },
    {
      "coverage_pct": null,
      "kinds_reachable": 3,
      "kinds_total": 3,
      "ts": 1782644547,
      "worst_lag_seconds": 3
    },
    {
      "coverage_pct": null,
      "kinds_reachable": 3,
      "kinds_total": 3,
      "ts": 1782653813,
      "worst_lag_seconds": 3
    },
    {
      "coverage_pct": null,
      "kinds_reachable": 3,
      "kinds_total": 3,
      "ts": 1782664554,
      "worst_lag_seconds": 1
    },
    {
      "coverage_pct": null,
      "kinds_reachable": 3,
      "kinds_total": 3,
      "ts": 1782675162,
      "worst_lag_seconds": 4
    },
    {
      "coverage_pct": null,
      "kinds_reachable": 3,
      "kinds_total": 3,
      "ts": 1782685847,
      "worst_lag_seconds": 4
    },
    {
      "coverage_pct": null,
      "kinds_reachable": 3,
      "kinds_total": 3,
      "ts": 1782699386,
      "worst_lag_seconds": 3
    },
    {
      "coverage_pct": null,
      "kinds_reachable": 3,
      "kinds_total": 3,
      "ts": 1782712066,
      "worst_lag_seconds": 3
    },
    {
      "coverage_pct": null,
      "kinds_reachable": 3,
      "kinds_total": 3,
      "ts": 1782723722,
      "worst_lag_seconds": 3
    },
    {
      "coverage_pct": null,
      "kinds_reachable": 3,
      "kinds_total": 3,
      "ts": 1782733645,
      "worst_lag_seconds": 4
    },
    {
      "coverage_pct": null,
      "kinds_reachable": 3,
      "kinds_total": 3,
      "ts": 1782743997,
      "worst_lag_seconds": 0
    },
    {
      "coverage_pct": null,
      "kinds_reachable": 3,
      "kinds_total": 3,
      "ts": 1782753664,
      "worst_lag_seconds": 5
    },
    {
      "coverage_pct": null,
      "kinds_reachable": 3,
      "kinds_total": 3,
      "ts": 1782762532,
      "worst_lag_seconds": 4
    },
    {
      "coverage_pct": null,
      "kinds_reachable": 3,
      "kinds_total": 3,
      "ts": 1782772645,
      "worst_lag_seconds": 4
    },
    {
      "coverage_pct": null,
      "kinds_reachable": 3,
      "kinds_total": 3,
      "ts": 1782785385,
      "worst_lag_seconds": 2
    },
    {
      "coverage_pct": null,
      "kinds_reachable": 3,
      "kinds_total": 3,
      "ts": 1782799919,
      "worst_lag_seconds": 4
    },
    {
      "coverage_pct": null,
      "kinds_reachable": 3,
      "kinds_total": 3,
      "ts": 1782808350,
      "worst_lag_seconds": 4
    },
    {
      "coverage_pct": null,
      "kinds_reachable": 3,
      "kinds_total": 3,
      "ts": 1782818589,
      "worst_lag_seconds": 5
    },
    {
      "coverage_pct": null,
      "kinds_reachable": 3,
      "kinds_total": 3,
      "ts": 1782827646,
      "worst_lag_seconds": 2
    },
    {
      "coverage_pct": null,
      "kinds_reachable": 3,
      "kinds_total": 3,
      "ts": 1782839047,
      "worst_lag_seconds": 0
    },
    {
      "coverage_pct": null,
      "kinds_reachable": 3,
      "kinds_total": 3,
      "ts": 1782849077,
      "worst_lag_seconds": 3
    },
    {
      "coverage_pct": null,
      "kinds_reachable": 3,
      "kinds_total": 3,
      "ts": 1782859561,
      "worst_lag_seconds": 3
    },
    {
      "coverage_pct": null,
      "kinds_reachable": 3,
      "kinds_total": 3,
      "ts": 1782872383,
      "worst_lag_seconds": 3
    },
    {
      "coverage_pct": null,
      "kinds_reachable": 3,
      "kinds_total": 3,
      "ts": 1782945835,
      "worst_lag_seconds": 4
    },
    {
      "coverage_pct": null,
      "kinds_reachable": 3,
      "kinds_total": 3,
      "ts": 1782958696,
      "worst_lag_seconds": 4
    },
    {
      "coverage_pct": null,
      "kinds_reachable": 3,
      "kinds_total": 3,
      "ts": 1782978343,
      "worst_lag_seconds": 4
    },
    {
      "coverage_pct": null,
      "kinds_reachable": 3,
      "kinds_total": 3,
      "ts": 1782995938,
      "worst_lag_seconds": 3
    },
    {
      "coverage_pct": null,
      "kinds_reachable": 3,
      "kinds_total": 3,
      "ts": 1783005841,
      "worst_lag_seconds": 2
    },
    {
      "coverage_pct": null,
      "kinds_reachable": 3,
      "kinds_total": 3,
      "ts": 1783015004,
      "worst_lag_seconds": 1
    },
    {
      "coverage_pct": null,
      "kinds_reachable": 3,
      "kinds_total": 3,
      "ts": 1783025230,
      "worst_lag_seconds": 0
    },
    {
      "coverage_pct": null,
      "kinds_reachable": 3,
      "kinds_total": 3,
      "ts": 1783034087,
      "worst_lag_seconds": 0
    },
    {
      "coverage_pct": null,
      "kinds_reachable": 3,
      "kinds_total": 3,
      "ts": 1783055029,
      "worst_lag_seconds": 5
    },
    {
      "coverage_pct": null,
      "kinds_reachable": 3,
      "kinds_total": 3,
      "ts": 1783074800,
      "worst_lag_seconds": 0
    },
    {
      "coverage_pct": null,
      "kinds_reachable": 3,
      "kinds_total": 3,
      "ts": 1783092530,
      "worst_lag_seconds": 3
    },
    {
      "coverage_pct": null,
      "kinds_reachable": 3,
      "kinds_total": 3,
      "ts": 1783159127,
      "worst_lag_seconds": 4
    },
    {
      "coverage_pct": null,
      "kinds_reachable": 3,
      "kinds_total": 3,
      "ts": 1783166241,
      "worst_lag_seconds": 4
    },
    {
      "coverage_pct": null,
      "kinds_reachable": 3,
      "kinds_total": 3,
      "ts": 1783176987,
      "worst_lag_seconds": 2
    },
    {
      "coverage_pct": null,
      "kinds_reachable": 3,
      "kinds_total": 3,
      "ts": 1783185293,
      "worst_lag_seconds": 5
    },
    {
      "coverage_pct": null,
      "kinds_reachable": 3,
      "kinds_total": 3,
      "ts": 1783197489,
      "worst_lag_seconds": 5
    },
    {
      "coverage_pct": null,
      "kinds_reachable": 3,
      "kinds_total": 3,
      "ts": 1783206755,
      "worst_lag_seconds": 4
    },
    {
      "coverage_pct": null,
      "kinds_reachable": 3,
      "kinds_total": 3,
      "ts": 1783229316,
      "worst_lag_seconds": 0
    },
    {
      "coverage_pct": null,
      "kinds_reachable": 3,
      "kinds_total": 3,
      "ts": 1783246826,
      "worst_lag_seconds": 0
    },
    {
      "coverage_pct": null,
      "kinds_reachable": 3,
      "kinds_total": 3,
      "ts": 1783264271,
      "worst_lag_seconds": 3
    },
    {
      "coverage_pct": null,
      "kinds_reachable": 3,
      "kinds_total": 3,
      "ts": 1783272326,
      "worst_lag_seconds": 4
    },
    {
      "coverage_pct": null,
      "kinds_reachable": 3,
      "kinds_total": 3,
      "ts": 1783284076,
      "worst_lag_seconds": 2
    }
  ],
  "summary": {
    "first_ts": 1782184747,
    "last_ts": 1783284076,
    "median_coverage_pct": null,
    "median_lag_seconds": 3,
    "observations": 87,
    "uptime_pct": 100.0
  }
}
